aeron/__init__.py
aeron/core.py
aeron-0.1.1.dist-info/LICENSE
aeron-0.1.1.dist-info/METADATA
aeron-0.1.1.dist-info/WHEEL
aeron-0.1.1.dist-info/top_level.txt
aeron-0.1.1.dist-info/RECORD
